[
    {
        "_id": "663b869cc98d8e02705119b7",
        "nameKey": "sass",
        "icon": "fa-brands fa-sass",
        "level": 4,
        "__v": 0
    },
    {
        "_id": "663b869cc98d8e02705119b9",
        "nameKey": "html",
        "icon": "fa-brands fa-html5",
        "level": 4,
        "__v": 0
    },
    {
        "_id": "663b869cc98d8e02705119b8",
        "nameKey": "css",
        "icon": "fa-brands fa-css3-alt",
        "level": 4,
        "__v": 0
    },
    {
        "_id": "663b869cc98d8e02705119b3",
        "nameKey": "javascript",
        "icon": "fa-brands fa-js",
        "level": 3,
        "__v": 0
    },
    {
        "_id": "663b869cc98d8e02705119b6",
        "nameKey": "react",
        "icon": "fa-brands fa-react",
        "level": 2,
        "__v": 0
    },
    {
        "_id": "663b869cc98d8e02705119b4",
        "nameKey": "mongodb",
        "icon": "fa-brands fa-envira",
        "level": 2,
        "__v": 0
    },
    {
        "_id": "663b869cc98d8e02705119b5",
        "nameKey": "nodejs",
        "icon": "fa-brands fa-node",
        "level": 2,
        "__v": 0
    }
]